async_dramatiq/__init__.py
async_dramatiq/actor.py
async_dramatiq/backends/__init__.py
async_dramatiq/backends/async_redis.py
async_dramatiq/backends/async_stub.py
async_dramatiq/middleware/__init__.py
async_dramatiq/middleware/async_base.py
async_dramatiq/middleware/async_stub.py
async_dramatiq/scheduler.py
async_dramatiq/types.py
async_dramatiq/worker.py
async_dramatiq-0.1.8.dist-info/LICENSE
async_dramatiq-0.1.8.dist-info/METADATA
async_dramatiq-0.1.8.dist-info/WHEEL
async_dramatiq-0.1.8.dist-info/RECORD
